open3d/__init__.py
open3d/_build_config.py
open3d/app.py
open3d/libc++.so.1
open3d/libc++abi.so.1
open3d/libtbb.so.12
open3d/web_visualizer.py
open3d/_ml3d/__init__.py
open3d/_ml3d/configs/__init__.py
open3d/_ml3d/configs/kpconv_parislille3d.yml
open3d/_ml3d/configs/kpconv_s3dis.yml
open3d/_ml3d/configs/kpconv_semantic3d.yml
open3d/_ml3d/configs/kpconv_semantickitti.yml
open3d/_ml3d/configs/kpconv_toronto3d.yml
open3d/_ml3d/configs/pointpillars_argoverse.yml
open3d/_ml3d/configs/pointpillars_kitti.yml
open3d/_ml3d/configs/pointpillars_lyft.yml
open3d/_ml3d/configs/pointpillars_nuscenes.yml
open3d/_ml3d/configs/pointpillars_waymo.yml
open3d/_ml3d/configs/pointrcnn_kitti.yml
open3d/_ml3d/configs/pointtransformer_s3dis.yml
open3d/_ml3d/configs/pvcnn_s3dis.yml
open3d/_ml3d/configs/randlanet_pandaset.yml
open3d/_ml3d/configs/randlanet_parislille3d.yml
open3d/_ml3d/configs/randlanet_s3dis.yml
open3d/_ml3d/configs/randlanet_semantic3d.yml
open3d/_ml3d/configs/randlanet_semantickitti.yml
open3d/_ml3d/configs/randlanet_toronto3d.yml
open3d/_ml3d/configs/sparseconvunet_scannet.yml
open3d/_ml3d/configs/torch_to_tf.yml
open3d/_ml3d/configs/default_cfgs/kpconv.yml
open3d/_ml3d/configs/default_cfgs/object_detection.yml
open3d/_ml3d/configs/default_cfgs/parislille3d.yml
open3d/_ml3d/configs/default_cfgs/randlanet.yml
open3d/_ml3d/configs/default_cfgs/s3dis.yml
open3d/_ml3d/configs/default_cfgs/semantic3d.yml
open3d/_ml3d/configs/default_cfgs/semantic_segmentation.yml
open3d/_ml3d/configs/default_cfgs/semantickitti.yml
open3d/_ml3d/configs/default_cfgs/shapenet.yml
open3d/_ml3d/configs/default_cfgs/toronto3d.yml
open3d/_ml3d/datasets/__init__.py
open3d/_ml3d/datasets/argoverse.py
open3d/_ml3d/datasets/base_dataset.py
open3d/_ml3d/datasets/customdataset.py
open3d/_ml3d/datasets/inference_dummy.py
open3d/_ml3d/datasets/kitti.py
open3d/_ml3d/datasets/lyft.py
open3d/_ml3d/datasets/matterport_objects.py
open3d/_ml3d/datasets/nuscenes.py
open3d/_ml3d/datasets/pandaset.py
open3d_cpu-0.19.0.dist-info/LICENSE.txt
open3d_cpu-0.19.0.dist-info/METADATA
open3d_cpu-0.19.0.dist-info/WHEEL
open3d_cpu-0.19.0.dist-info/entry_points.txt
open3d_cpu-0.19.0.dist-info/top_level.txt
open3d_cpu-0.19.0.dist-info/RECORD
